CHANGES
LICENSE
MANIFEST.in
README.rst
setup.py
django_multi_email_field_rerelease.egg-info/PKG-INFO
django_multi_email_field_rerelease.egg-info/SOURCES.txt
django_multi_email_field_rerelease.egg-info/dependency_links.txt
django_multi_email_field_rerelease.egg-info/not-zip-safe
django_multi_email_field_rerelease.egg-info/requires.txt
django_multi_email_field_rerelease.egg-info/top_level.txt
multi_email_field/__init__.py
multi_email_field/fields.py
multi_email_field/forms.py
multi_email_field/models.py
multi_email_field/tests.py
multi_email_field/widgets.py