Metadata-Version: 1.1
Name: django-multi-email-field-rerelease
Version: 0.5
Summary: Provides a model field and a form field to manage list of e-mails
Home-page: https://github.com/fle/django-multi-email-field
Author: Florent Lebreton
Author-email: florent.lebreton@makina-corpus.com
License: LGPL, see LICENSE file.
Platform: UNKNOWN
Classifier: Topic :: Utilities
Classifier: Natural Language :: English
Classifier: Operating System :: OS Independent
Classifier: Intended Audience :: Developers
Classifier: Environment :: Web Environment
Classifier: Framework :: Django
Classifier: Development Status :: 5 - Production/Stable
Classifier: Programming Language :: Python
Classifier: Programming Language :: Python :: 2.7
Classifier: Programming Language :: Python :: 3.2
Classifier: Programming Language :: Python :: 3.3
Classifier: Programming Language :: Python :: 3.4
Classifier: Programming Language :: Python :: 3.5
